{
  "format": "douluo-spin-long-simulation",
  "formatVersion": 1,
  "generatedAt": "2026-07-16T15:48:54.654Z",
  "seed": "mrnop1p1-0pln8351a8tizu-sample-002",
  "requestedRolls": 500,
  "executedRolls": 66,
  "completed": true,
  "samplingMode": "weighted",
  "audit": {
    "passed": true,
    "issues": []
  },
  "biography": "《斗罗大陆 · 命运轮盘人物传记》\n\n【命运档案】\n命运种子：mrnop1p1-0pln8351a8tizu-sample-002\n姓名：命运旅者\n路线：人类魂师\n时间坐标：唐三 26 岁\n实际年龄：24岁\n当前境界：58级（上限99级）\n命运状态：你走过斗罗大陆主线年代，命运进入新的时代。\n阵营履历：诺丁初级魂师学院 · 五元素学院 · 史莱克学院任职教师\n\n【人物身份】\n性别：男\n容貌：E\n武魂类型：器武魂\n主武魂：混天披风\n\n【能力与机缘】\n特殊天赋：无\n称号与特质：启蒙期·6-11岁、成长期·12-17岁、担当期·18岁+、精英职责·18岁+·50级+\n领域：无\n魂骨：300年外附魂骨、300年右腿骨、700年左腿骨、1800年左臂骨、1000年躯干骨、10000年右臂骨\n神考：神祇未定｜三级神考｜0/7\n\n【魂环明细】\n- 第1魂环｜300年｜300年魂环\n- 第2魂环｜700年｜700年魂环\n- 第3魂环｜1800年｜1800年魂环\n- 第4魂环｜1000年｜1000年魂环\n- 第5魂环｜10000年｜10000年魂环\n\n【命运纪事】\n时间未定｜命运启封｜种子：mrnop1p1-0pln8351a8tizu-sample-002\n时间未定｜基础设定3:你的性别是？｜男\n时间未定｜基础设定4:容貌（B级以下无法恋爱）｜E级（有点丑）\n时间未定｜基础设定5:武魂天赋｜器武魂\n时间未定｜器武魂分类｜披风锁链\n时间未定｜器武魂：披风锁链｜混天披风\n时间未定｜基础设定6:是否拥有特殊天赋｜否\n6岁｜基础设定7:你的年龄｜6岁\n唐三 8 岁｜基础设定8:穿越时期｜唐三8岁\n唐三 8 岁｜先天魂力（6岁限定）｜4级\n唐三 8 岁｜人物背景or加入的势力（6岁限定）｜诺丁初级魂师学院\n唐三 8 岁｜势力专属剧情：天斗学院体系｜【启蒙期·6-11岁】学院安排你参加基础联考，你靠稳定魂力控制通过第一次分班\n唐三 10 岁｜2年后，你的成长（6岁-12岁限定，已达12岁则不可再抽取该池）｜等级+6\n唐三 10 岁｜是否获得特殊成长经历（每次经过一次时间跳跃，可抽取该池）｜否，无事发生\n唐三 10 岁｜魂环吸收（第一魂环）（抽取完魂环后请进入对应的魂骨抽奖池）｜300年魂环\n唐三 10 岁｜魂骨抽取池（已拥有部位则重抽）｜外附魂骨\n唐三 12 岁｜2年后，你的成长（6岁-12岁限定，已达12岁则不可再抽取该池）｜等级+4\n唐三 12 岁｜是否获得特殊成长经历（每次经过一次时间跳跃，可抽取该池）｜是\n唐三 12 岁｜特殊成长经历｜获得神考（要求15岁以下40级以上，20岁以下60级以上，25岁以下70级以上，30岁以下90级以上，否则重抽）（已拥有神考无法叠加则重抽）\n唐三 12 岁｜神考池子｜二级神考核\n唐三 12 岁｜二级神考抽取池（二级神一共8考）｜自创神位（自定义神名，二级神，8考）\n唐三 12 岁｜剧情1:是否参与入学剧情（非史莱克or武魂殿学员限定）｜是\n唐三 12 岁｜剧情2:在校2年的经历选择（非史莱克or武魂殿学员限定）｜默默无闻，一直闭关\n唐三 14 岁｜2年后，你的成长（6岁-12岁限定，已达12岁则不可再抽取该池）｜等级+4\n唐三 14 岁｜是否获得特殊成长经历（每次经过一次时间跳跃，可抽取该池）｜否，无事发生\n唐三 14 岁｜加入的势力（12岁限定）｜五元素学院\n唐三 14 岁｜势力专属剧情：天斗学院体系｜【成长期·12-17岁】你参加学院交流赛，以一次主动换位挽回被压制的小队\n唐三 14 岁｜剧情3:是否参与参加团队核心竞争（魂师大赛前限定抽取池，此时唐三14岁）｜否，你不感兴趣（默认不参加魂师学院大赛剧情）\n唐三 14 岁｜剧情4:魂师学院大赛预选赛结果｜拖后腿，导致团队落败（35级以下限定，高于35级则重抽）\n唐三 14 岁｜剧情5:单人赛结果｜因为你的自傲，开局被唐三击败，你的学院单人赛落败（45+级则可以重抽）\n唐三 14 岁｜剧情6:决赛结果｜与队友配合对战黄金一代重伤获胜（45+限定，否则重抽）\n唐三 16 岁｜2年后，你的成长（12岁-18岁限定，已达18岁不可再抽取该池）（没有神位最多到99级）｜等级+4级\n唐三 16 岁｜是否获得特殊成长经历（每次经过一次时间跳跃，可抽取该池）｜是\n唐三 16 岁｜特殊成长经历｜获得对应吸收上限的魂骨（进入魂骨抽取池）\n唐三 16 岁｜魂骨抽取池（已拥有部位则重抽）｜右腿骨\n唐三 16 岁｜魂环吸收（第二魂环）（抽取完魂环后请进入对应的魂骨抽奖池）｜700年魂环\n唐三 16 岁｜魂骨抽取池（已拥有部位则重抽）｜左腿骨\n唐三 18 岁｜2年后，你的成长（12岁-18岁限定，已达18岁不可再抽取该池）（没有神位最多到99级）｜等级+8级\n唐三 18 岁｜是否获得特殊成长经历（每次经过一次时间跳跃，可抽取该池）｜是\n唐三 18 岁｜特殊成长经历｜略有领悟（等级+3）\n唐三 18 岁｜魂环吸收（第三魂环）（抽取完魂环后请进入对应的魂骨抽奖池）｜1800年魂环\n唐三 18 岁｜魂骨抽取池（已拥有部位则重抽）｜左臂骨\n唐三 18 岁｜是否进入杀戮之都（角色在16岁~22岁限定事件，未满足年龄不能抽取）｜否\n唐三 20 岁｜2年后，你的成长（12岁-18岁限定，已达18岁不可再抽取该池）（没有神位最多到99级）｜等级+9级\n唐三 20 岁｜是否获得特殊成长经历（每次经过一次时间跳跃，可抽取该池）｜否，无事发生\n唐三 20 岁｜魂环吸收（第四魂环）（抽取完魂环后请进入对应的魂骨抽奖池）｜1000年魂环\n唐三 20 岁｜魂骨抽取池（已拥有部位则重抽）｜躯干骨\n唐三 20 岁｜二级神考核第一考奖励（要求40级以上才可以抽取）｜获得一块6万年魂骨（进入魂骨抽取池）\n唐三 20 岁｜加入的势力（18岁限定）｜史莱克学院任职教师（进入剧情分支一）\n唐三 20 岁｜势力专属剧情：史莱克学院｜【担当期·18岁+】你协助学院整理学员魂环风险档案，开始承担正式教学或护校事务\n唐三 20 岁｜剧情14:是否参与天斗宫变（此时唐三20岁）｜是，在外围援护\n唐三 20 岁｜剧情15:唐三重建唐门，邀请你加入唐门担任其中一个堂主or副门主的职位（70+级会邀请你当副门主，70级以下则堂主）｜同意加入，但你婉拒堂主or副门主的职位\n唐三 22 岁｜2年后，你的成长（18岁+的年龄通用池）（无神位最多只能达到99级）｜等级+1\n唐三 22 岁｜是否获得特殊成长经历（每次经过一次时间跳跃，可抽取该池）｜否，无事发生\n唐三 22 岁｜剧情16:七怪打算前往海神岛，你是否前往（唐三21岁限定）｜是，前往海神岛（进入海神考核奖池选择你的考核）\n唐三 24 岁｜2年后，你的成长（18岁+的年龄通用池）（无神位最多只能达到99级）｜等级+9\n唐三 24 岁｜是否获得特殊成长经历（每次经过一次时间跳跃，可抽取该池）｜是\n唐三 24 岁｜特殊成长经历｜略有领悟（等级+3）\n唐三 24 岁｜魂环吸收（第五魂环）（抽取完魂环后请进入对应的魂骨抽奖池）｜10000年魂环\n唐三 24 岁｜魂骨抽取池（已拥有部位则重抽）｜右臂骨\n唐三 24 岁｜二级神考核第二考奖励（要求50级以上才可抽取）｜获得一块7万年魂骨（进入魂骨抽取池）\n唐三 24 岁｜势力专属剧情：史莱克学院｜【精英职责·18岁+·50级+】你受托审查高年级实战考核，在关键时刻叫停一场失控对决\n唐三 26 岁｜2年后，你的成长（18岁+的年龄通用池）（无神位最多只能达到99级）｜等级+3\n唐三 26 岁｜是否获得特殊成长经历（每次经过一次时间跳跃，可抽取该池）｜是\n唐三 26 岁｜特殊成长经历｜获得神考（要求15岁以下40级以上，20岁以下60级以上，25岁以下70级以上，30岁以下90级以上，否则重抽）（已拥有神考无法叠加则重抽）\n唐三 26 岁｜神考池子｜三级神考核\n唐三 26 岁｜三级神考抽取池（三级神一共7考）｜自创神位（自定义神名，三级神，7考）\n唐三 26 岁｜命运终章｜你走过斗罗大陆主线年代，命运进入新的时代。",
  "trace": [
    {
      "roll": 1,
      "pool": "基础设定3:你的性别是？",
      "optionId": "b34683",
      "option": "男",
      "probability": 0.47619047619047616,
      "level": 0,
      "soulBoneCount": 0,
      "queuedNextPool": "基础设定4:容貌（B级以下无法恋爱）"
    },
    {
      "roll": 2,
      "pool": "基础设定4:容貌（B级以下无法恋爱）",
      "optionId": "4e3f46",
      "option": "E级（有点丑）",
      "probability": 0.12345679012345678,
      "level": 0,
      "soulBoneCount": 0,
      "queuedNextPool": "基础设定5:武魂天赋"
    },
    {
      "roll": 3,
      "pool": "基础设定5:武魂天赋",
      "optionId": "6f2ee4",
      "option": "器武魂",
      "probability": 0.3611111111111111,
      "level": 0,
      "soulBoneCount": 0,
      "queuedNextPool": "器武魂分类"
    },
    {
      "roll": 4,
      "pool": "器武魂分类",
      "optionId": "tool-martial-category-披风锁链",
      "option": "披风锁链",
      "probability": 0.02247191011235955,
      "level": 0,
      "soulBoneCount": 0,
      "queuedNextPool": "器武魂：披风锁链"
    },
    {
      "roll": 5,
      "pool": "器武魂：披风锁链",
      "optionId": "9c7399",
      "option": "混天披风",
      "probability": 0.5,
      "level": 0,
      "soulBoneCount": 0,
      "queuedNextPool": "基础设定6:是否拥有特殊天赋"
    },
    {
      "roll": 6,
      "pool": "基础设定6:是否拥有特殊天赋",
      "optionId": "3c9407",
      "option": "否",
      "probability": 0.75,
      "level": 0,
      "soulBoneCount": 0,
      "queuedNextPool": "基础设定7:你的年龄"
    },
    {
      "roll": 7,
      "pool": "基础设定7:你的年龄",
      "optionId": "6dcd60",
      "option": "6岁",
      "probability": 0.7258064516129032,
      "level": 0,
      "soulBoneCount": 0,
      "queuedNextPool": "基础设定8:穿越时期"
    },
    {
      "roll": 8,
      "pool": "基础设定8:穿越时期",
      "optionId": "6489bc",
      "option": "唐三8岁",
      "probability": 0.032119914346895075,
      "level": 0,
      "soulBoneCount": 0,
      "queuedNextPool": "先天魂力（6岁限定）"
    },
    {
      "roll": 9,
      "pool": "先天魂力（6岁限定）",
      "optionId": "c4defd",
      "option": "4级",
      "probability": 0.13078960482011195,
      "level": 4,
      "soulBoneCount": 0,
      "queuedNextPool": "人物背景or加入的势力（6岁限定）"
    },
    {
      "roll": 10,
      "pool": "人物背景or加入的势力（6岁限定）",
      "optionId": "ab3707",
      "option": "诺丁初级魂师学院",
      "probability": 0.11494252873563218,
      "level": 4,
      "soulBoneCount": 0,
      "queuedNextPool": null
    },
    {
      "roll": 11,
      "pool": "势力专属剧情：天斗学院体系",
      "optionId": "faction-story-academy-1",
      "option": "【启蒙期·6-11岁】学院安排你参加基础联考，你靠稳定魂力控制通过第一次分班",
      "probability": 0.6666666666666666,
      "level": 4,
      "soulBoneCount": 0,
      "queuedNextPool": "2年后，你的成长（6岁-12岁限定，已达12岁则不可再抽取该池）"
    },
    {
      "roll": 12,
      "pool": "2年后，你的成长（6岁-12岁限定，已达12岁则不可再抽取该池）",
      "optionId": "f32246",
      "option": "等级+6",
      "probability": 0.11363636363636363,
      "level": 10,
      "soulBoneCount": 0,
      "queuedNextPool": "是否获得特殊成长经历（每次经过一次时间跳跃，可抽取该池）"
    },
    {
      "roll": 13,
      "pool": "是否获得特殊成长经历（每次经过一次时间跳跃，可抽取该池）",
      "optionId": "1bb6e2",
      "option": "否，无事发生",
      "probability": 0.6,
      "level": 10,
      "soulBoneCount": 0,
      "queuedNextPool": "魂环吸收（第一魂环）（抽取完魂环后请进入对应的魂骨抽奖池）"
    },
    {
      "roll": 14,
      "pool": "魂环吸收（第一魂环）（抽取完魂环后请进入对应的魂骨抽奖池）",
      "optionId": "4371de",
      "option": "300年魂环",
      "probability": 0.1111111111111111,
      "level": 10,
      "soulBoneCount": 0,
      "queuedNextPool": "魂骨抽取池（已拥有部位则重抽）"
    },
    {
      "roll": 15,
      "pool": "魂骨抽取池（已拥有部位则重抽）",
      "optionId": "9a5039",
      "option": "外附魂骨",
      "probability": 0.03773584905660377,
      "level": 10,
      "soulBoneCount": 1,
      "queuedNextPool": "2年后，你的成长（6岁-12岁限定，已达12岁则不可再抽取该池）"
    },
    {
      "roll": 16,
      "pool": "2年后，你的成长（6岁-12岁限定，已达12岁则不可再抽取该池）",
      "optionId": "2f2851",
      "option": "等级+4",
      "probability": 0.1590909090909091,
      "level": 14,
      "soulBoneCount": 1,
      "queuedNextPool": "是否获得特殊成长经历（每次经过一次时间跳跃，可抽取该池）"
    },
    {
      "roll": 17,
      "pool": "是否获得特殊成长经历（每次经过一次时间跳跃，可抽取该池）",
      "optionId": "bc5322",
      "option": "是",
      "probability": 0.4,
      "level": 14,
      "soulBoneCount": 1,
      "queuedNextPool": "特殊成长经历"
    },
    {
      "roll": 18,
      "pool": "特殊成长经历",
      "optionId": "a9257d",
      "option": "获得神考（要求15岁以下40级以上，20岁以下60级以上，25岁以下70级以上，30岁以下90级以上，否则重抽）（已拥有神考无法叠加则重抽）",
      "probability": 0.14705882352941177,
      "level": 14,
      "soulBoneCount": 1,
      "queuedNextPool": "神考池子"
    },
    {
      "roll": 19,
      "pool": "神考池子",
      "optionId": "a46067",
      "option": "二级神考核",
      "probability": 0.47619047619047616,
      "level": 14,
      "soulBoneCount": 1,
      "queuedNextPool": "二级神考抽取池（二级神一共8考）"
    },
    {
      "roll": 20,
      "pool": "二级神考抽取池（二级神一共8考）",
      "optionId": "61a10e",
      "option": "自创神位（自定义神名，二级神，8考）",
      "probability": 0.25,
      "level": 14,
      "soulBoneCount": 1,
      "queuedNextPool": "剧情1:是否参与入学剧情（非史莱克or武魂殿学员限定）"
    },
    {
      "roll": 21,
      "pool": "剧情1:是否参与入学剧情（非史莱克or武魂殿学员限定）",
      "optionId": "bacd06",
      "option": "是",
      "probability": 0.6,
      "level": 14,
      "soulBoneCount": 1,
      "queuedNextPool": "剧情2:在校2年的经历选择（非史莱克or武魂殿学员限定）"
    },
    {
      "roll": 22,
      "pool": "剧情2:在校2年的经历选择（非史莱克or武魂殿学员限定）",
      "optionId": "4c752a",
      "option": "默默无闻，一直闭关",
      "probability": 0.21875,
      "level": 14,
      "soulBoneCount": 1,
      "queuedNextPool": "2年后，你的成长（6岁-12岁限定，已达12岁则不可再抽取该池）"
    },
    {
      "roll": 23,
      "pool": "2年后，你的成长（6岁-12岁限定，已达12岁则不可再抽取该池）",
      "optionId": "2f2851",
      "option": "等级+4",
      "probability": 0.1590909090909091,
      "level": 18,
      "soulBoneCount": 1,
      "queuedNextPool": "是否获得特殊成长经历（每次经过一次时间跳跃，可抽取该池）"
    },
    {
      "roll": 24,
      "pool": "是否获得特殊成长经历（每次经过一次时间跳跃，可抽取该池）",
      "optionId": "1bb6e2",
      "option": "否，无事发生",
      "probability": 0.6,
      "level": 18,
      "soulBoneCount": 1,
      "queuedNextPool": "加入的势力（12岁限定）"
    },
    {
      "roll": 25,
      "pool": "加入的势力（12岁限定）",
      "optionId": "7c31f1",
      "option": "五元素学院",
      "probability": 0.07317073170731707,
      "level": 18,
      "soulBoneCount": 1,
      "queuedNextPool": "势力专属剧情：天斗学院体系"
    },
    {
      "roll": 26,
      "pool": "势力专属剧情：天斗学院体系",
      "optionId": "faction-story-academy-4",
      "option": "【成长期·12-17岁】你参加学院交流赛，以一次主动换位挽回被压制的小队",
      "probability": 0.6666666666666666,
      "level": 18,
      "soulBoneCount": 1,
      "queuedNextPool": "剧情3:是否参与参加团队核心竞争（魂师大赛前限定抽取池，此时唐三14岁）"
    },
    {
      "roll": 27,
      "pool": "剧情3:是否参与参加团队核心竞争（魂师大赛前限定抽取池，此时唐三14岁）",
      "optionId": "20d384",
      "option": "否，你不感兴趣（默认不参加魂师学院大赛剧情）",
      "probability": 1,
      "level": 18,
      "soulBoneCount": 1,
      "queuedNextPool": "剧情4:魂师学院大赛预选赛结果"
    },
    {
      "roll": 28,
      "pool": "剧情4:魂师学院大赛预选赛结果",
      "optionId": "849e29",
      "option": "拖后腿，导致团队落败（35级以下限定，高于35级则重抽）",
      "probability": 1,
      "level": 18,
      "soulBoneCount": 1,
      "queuedNextPool": "剧情5:单人赛结果"
    },
    {
      "roll": 29,
      "pool": "剧情5:单人赛结果",
      "optionId": "b93cc6",
      "option": "因为你的自傲，开局被唐三击败，你的学院单人赛落败（45+级则可以重抽）",
      "probability": 0.21841321974751102,
      "level": 18,
      "soulBoneCount": 1,
      "queuedNextPool": "剧情6:决赛结果"
    },
    {
      "roll": 30,
      "pool": "剧情6:决赛结果",
      "optionId": "5e65c9",
      "option": "与队友配合对战黄金一代重伤获胜（45+限定，否则重抽）",
      "probability": 0.8209876543209876,
      "level": 18,
      "soulBoneCount": 1,
      "queuedNextPool": "2年后，你的成长（12岁-18岁限定，已达18岁不可再抽取该池）（没有神位最多到99级）"
    },
    {
      "roll": 31,
      "pool": "2年后，你的成长（12岁-18岁限定，已达18岁不可再抽取该池）（没有神位最多到99级）",
      "optionId": "954785",
      "option": "等级+4级",
      "probability": 0.0970873786407767,
      "level": 22,
      "soulBoneCount": 1,
      "queuedNextPool": "是否获得特殊成长经历（每次经过一次时间跳跃，可抽取该池）"
    },
    {
      "roll": 32,
      "pool": "是否获得特殊成长经历（每次经过一次时间跳跃，可抽取该池）",
      "optionId": "bc5322",
      "option": "是",
      "probability": 0.4,
      "level": 22,
      "soulBoneCount": 1,
      "queuedNextPool": "特殊成长经历"
    },
    {
      "roll": 33,
      "pool": "特殊成长经历",
      "optionId": "317246",
      "option": "获得对应吸收上限的魂骨（进入魂骨抽取池）",
      "probability": 0.049019607843137254,
      "level": 22,
      "soulBoneCount": 1,
      "queuedNextPool": "魂骨抽取池（已拥有部位则重抽）"
    },
    {
      "roll": 34,
      "pool": "魂骨抽取池（已拥有部位则重抽）",
      "optionId": "082528",
      "option": "右腿骨",
      "probability": 0.19607843137254902,
      "level": 22,
      "soulBoneCount": 2,
      "queuedNextPool": "魂环吸收（第二魂环）（抽取完魂环后请进入对应的魂骨抽奖池）"
    },
    {
      "roll": 35,
      "pool": "魂环吸收（第二魂环）（抽取完魂环后请进入对应的魂骨抽奖池）",
      "optionId": "0a6083",
      "option": "700年魂环",
      "probability": 0.1267605633802817,
      "level": 22,
      "soulBoneCount": 2,
      "queuedNextPool": "魂骨抽取池（已拥有部位则重抽）"
    },
    {
      "roll": 36,
      "pool": "魂骨抽取池（已拥有部位则重抽）",
      "optionId": "5c21d5",
      "option": "左腿骨",
      "probability": 0.24390243902439024,
      "level": 22,
      "soulBoneCount": 3,
      "queuedNextPool": "2年后，你的成长（12岁-18岁限定，已达18岁不可再抽取该池）（没有神位最多到99级）"
    },
    {
      "roll": 37,
      "pool": "2年后，你的成长（12岁-18岁限定，已达18岁不可再抽取该池）（没有神位最多到99级）",
      "optionId": "571dcd",
      "option": "等级+8级",
      "probability": 0.0970873786407767,
      "level": 30,
      "soulBoneCount": 3,
      "queuedNextPool": "是否获得特殊成长经历（每次经过一次时间跳跃，可抽取该池）"
    },
    {
      "roll": 38,
      "pool": "是否获得特殊成长经历（每次经过一次时间跳跃，可抽取该池）",
      "optionId": "bc5322",
      "option": "是",
      "probability": 0.4,
      "level": 30,
      "soulBoneCount": 3,
      "queuedNextPool": "特殊成长经历"
    },
    {
      "roll": 39,
      "pool": "特殊成长经历",
      "optionId": "737f0b",
      "option": "略有领悟（等级+3）",
      "probability": 0.24509803921568626,
      "level": 33,
      "soulBoneCount": 3,
      "queuedNextPool": "魂环吸收（第三魂环）（抽取完魂环后请进入对应的魂骨抽奖池）"
    },
    {
      "roll": 40,
      "pool": "魂环吸收（第三魂环）（抽取完魂环后请进入对应的魂骨抽奖池）",
      "optionId": "4066bd",
      "option": "1800年魂环",
      "probability": 0.08411214953271028,
      "level": 33,
      "soulBoneCount": 3,
      "queuedNextPool": "魂骨抽取池（已拥有部位则重抽）"
    },
    {
      "roll": 41,
      "pool": "魂骨抽取池（已拥有部位则重抽）",
      "optionId": "672129",
      "option": "左臂骨",
      "probability": 0.3225806451612903,
      "level": 33,
      "soulBoneCount": 4,
      "queuedNextPool": "是否进入杀戮之都（角色在16岁~22岁限定事件，未满足年龄不能抽取）"
    },
    {
      "roll": 42,
      "pool": "是否进入杀戮之都（角色在16岁~22岁限定事件，未满足年龄不能抽取）",
      "optionId": "ca2dea",
      "option": "否",
      "probability": 0.4,
      "level": 33,
      "soulBoneCount": 4,
      "queuedNextPool": "2年后，你的成长（12岁-18岁限定，已达18岁不可再抽取该池）（没有神位最多到99级）"
    },
    {
      "roll": 43,
      "pool": "2年后，你的成长（12岁-18岁限定，已达18岁不可再抽取该池）（没有神位最多到99级）",
      "optionId": "6116a4",
      "option": "等级+9级",
      "probability": 0.07766990291262135,
      "level": 42,
      "soulBoneCount": 4,
      "queuedNextPool": "是否获得特殊成长经历（每次经过一次时间跳跃，可抽取该池）"
    },
    {
      "roll": 44,
      "pool": "是否获得特殊成长经历（每次经过一次时间跳跃，可抽取该池）",
      "optionId": "1bb6e2",
      "option": "否，无事发生",
      "probability": 0.6,
      "level": 42,
      "soulBoneCount": 4,
      "queuedNextPool": "魂环吸收（第四魂环）（抽取完魂环后请进入对应的魂骨抽奖池）"
    },
    {
      "roll": 45,
      "pool": "魂环吸收（第四魂环）（抽取完魂环后请进入对应的魂骨抽奖池）",
      "optionId": "f9b7ba",
      "option": "1000年魂环",
      "probability": 0.10344827586206896,
      "level": 42,
      "soulBoneCount": 4,
      "queuedNextPool": "魂骨抽取池（已拥有部位则重抽）"
    },
    {
      "roll": 46,
      "pool": "魂骨抽取池（已拥有部位则重抽）",
      "optionId": "751286",
      "option": "躯干骨",
      "probability": 0.2857142857142857,
      "level": 42,
      "soulBoneCount": 5,
      "queuedNextPool": "二级神考核第一考奖励（要求40级以上才可以抽取）"
    },
    {
      "roll": 47,
      "pool": "二级神考核第一考奖励（要求40级以上才可以抽取）",
      "optionId": "d39438",
      "option": "获得一块6万年魂骨（进入魂骨抽取池）",
      "probability": 0.21212121212121213,
      "level": 42,
      "soulBoneCount": 5,
      "queuedNextPool": "加入的势力（18岁限定）"
    },
    {
      "roll": 48,
      "pool": "加入的势力（18岁限定）",
      "optionId": "598f93",
      "option": "史莱克学院任职教师（进入剧情分支一）",
      "probability": 0.24096385542168675,
      "level": 42,
      "soulBoneCount": 5,
      "queuedNextPool": "势力专属剧情：史莱克学院"
    },
    {
      "roll": 49,
      "pool": "势力专属剧情：史莱克学院",
      "optionId": "faction-story-shrek-7",
      "option": "【担当期·18岁+】你协助学院整理学员魂环风险档案，开始承担正式教学或护校事务",
      "probability": 0.6666666666666666,
      "level": 42,
      "soulBoneCount": 5,
      "queuedNextPool": "剧情14:是否参与天斗宫变（此时唐三20岁）"
    },
    {
      "roll": 50,
      "pool": "剧情14:是否参与天斗宫变（此时唐三20岁）",
      "optionId": "e7b0b2",
      "option": "是，在外围援护",
      "probability": 0.5185185185185185,
      "level": 42,
      "soulBoneCount": 5,
      "queuedNextPool": "剧情15:唐三重建唐门，邀请你加入唐门担任其中一个堂主or副门主的职位（70+级会邀请你当副门主，70级以下则堂主）"
    },
    {
      "roll": 51,
      "pool": "剧情15:唐三重建唐门，邀请你加入唐门担任其中一个堂主or副门主的职位（70+级会邀请你当副门主，70级以下则堂主）",
      "optionId": "bfb38a",
      "option": "同意加入，但你婉拒堂主or副门主的职位",
      "probability": 0.17857142857142858,
      "level": 42,
      "soulBoneCount": 5,
      "queuedNextPool": "2年后，你的成长（18岁+的年龄通用池）（无神位最多只能达到99级）"
    },
    {
      "roll": 52,
      "pool": "2年后，你的成长（18岁+的年龄通用池）（无神位最多只能达到99级）",
      "optionId": "7ca960",
      "option": "等级+1",
      "probability": 0.052083333333333336,
      "level": 43,
      "soulBoneCount": 5,
      "queuedNextPool": "是否获得特殊成长经历（每次经过一次时间跳跃，可抽取该池）"
    },
    {
      "roll": 53,
      "pool": "是否获得特殊成长经历（每次经过一次时间跳跃，可抽取该池）",
      "optionId": "1bb6e2",
      "option": "否，无事发生",
      "probability": 0.6,
      "level": 43,
      "soulBoneCount": 5,
      "queuedNextPool": "剧情16:七怪打算前往海神岛，你是否前往（唐三21岁限定）"
    },
    {
      "roll": 54,
      "pool": "剧情16:七怪打算前往海神岛，你是否前往（唐三21岁限定）",
      "optionId": "e0eb42",
      "option": "是，前往海神岛（进入海神考核奖池选择你的考核）",
      "probability": 0.47058823529411764,
      "level": 43,
      "soulBoneCount": 5,
      "queuedNextPool": "2年后，你的成长（18岁+的年龄通用池）（无神位最多只能达到99级）"
    },
    {
      "roll": 55,
      "pool": "2年后，你的成长（18岁+的年龄通用池）（无神位最多只能达到99级）",
      "optionId": "3d2f3b",
      "option": "等级+9",
      "probability": 0.052083333333333336,
      "level": 52,
      "soulBoneCount": 5,
      "queuedNextPool": "是否获得特殊成长经历（每次经过一次时间跳跃，可抽取该池）"
    },
    {
      "roll": 56,
      "pool": "是否获得特殊成长经历（每次经过一次时间跳跃，可抽取该池）",
      "optionId": "bc5322",
      "option": "是",
      "probability": 0.4,
      "level": 52,
      "soulBoneCount": 5,
      "queuedNextPool": "特殊成长经历"
    },
    {
      "roll": 57,
      "pool": "特殊成长经历",
      "optionId": "737f0b",
      "option": "略有领悟（等级+3）",
      "probability": 0.24509803921568626,
      "level": 55,
      "soulBoneCount": 5,
      "queuedNextPool": "魂环吸收（第五魂环）（抽取完魂环后请进入对应的魂骨抽奖池）"
    },
    {
      "roll": 58,
      "pool": "魂环吸收（第五魂环）（抽取完魂环后请进入对应的魂骨抽奖池）",
      "optionId": "8c968c",
      "option": "10000年魂环",
      "probability": 0.1111111111111111,
      "level": 55,
      "soulBoneCount": 5,
      "queuedNextPool": "魂骨抽取池（已拥有部位则重抽）"
    },
    {
      "roll": 59,
      "pool": "魂骨抽取池（已拥有部位则重抽）",
      "optionId": "7f9b7a",
      "option": "右臂骨",
      "probability": 0.6666666666666666,
      "level": 55,
      "soulBoneCount": 6,
      "queuedNextPool": "二级神考核第二考奖励（要求50级以上才可抽取）"
    },
    {
      "roll": 60,
      "pool": "二级神考核第二考奖励（要求50级以上才可抽取）",
      "optionId": "57beab",
      "option": "获得一块7万年魂骨（进入魂骨抽取池）",
      "probability": 0.21212121212121213,
      "level": 55,
      "soulBoneCount": 6,
      "queuedNextPool": "势力专属剧情：史莱克学院"
    },
    {
      "roll": 61,
      "pool": "势力专属剧情：史莱克学院",
      "optionId": "faction-story-shrek-10",
      "option": "【精英职责·18岁+·50级+】你受托审查高年级实战考核，在关键时刻叫停一场失控对决",
      "probability": 0.6666666666666666,
      "level": 55,
      "soulBoneCount": 6,
      "queuedNextPool": "2年后，你的成长（18岁+的年龄通用池）（无神位最多只能达到99级）"
    },
    {
      "roll": 62,
      "pool": "2年后，你的成长（18岁+的年龄通用池）（无神位最多只能达到99级）",
      "optionId": "4f16c9",
      "option": "等级+3",
      "probability": 0.10416666666666667,
      "level": 58,
      "soulBoneCount": 6,
      "queuedNextPool": "是否获得特殊成长经历（每次经过一次时间跳跃，可抽取该池）"
    },
    {
      "roll": 63,
      "pool": "是否获得特殊成长经历（每次经过一次时间跳跃，可抽取该池）",
      "optionId": "bc5322",
      "option": "是",
      "probability": 0.4,
      "level": 58,
      "soulBoneCount": 6,
      "queuedNextPool": "特殊成长经历"
    },
    {
      "roll": 64,
      "pool": "特殊成长经历",
      "optionId": "a9257d",
      "option": "获得神考（要求15岁以下40级以上，20岁以下60级以上，25岁以下70级以上，30岁以下90级以上，否则重抽）（已拥有神考无法叠加则重抽）",
      "probability": 0.14705882352941177,
      "level": 58,
      "soulBoneCount": 6,
      "queuedNextPool": "神考池子"
    },
    {
      "roll": 65,
      "pool": "神考池子",
      "optionId": "d33dec",
      "option": "三级神考核",
      "probability": 0.23809523809523808,
      "level": 58,
      "soulBoneCount": 6,
      "queuedNextPool": "三级神考抽取池（三级神一共7考）"
    },
    {
      "roll": 66,
      "pool": "三级神考抽取池（三级神一共7考）",
      "optionId": "5e5c3a",
      "option": "自创神位（自定义神名，三级神，7考）",
      "probability": 0.16666666666666666,
      "level": 58,
      "soulBoneCount": 6,
      "queuedNextPool": null
    }
  ],
  "state": {
    "value": "ending",
    "context": {
      "seed": "mrnop1p1-0pln8351a8tizu-sample-002",
      "rng": 2860686542,
      "route": "human",
      "name": "命运旅者",
      "step": 66,
      "age": 24,
      "tangAge": 26,
      "gender": "男",
      "appearance": "E",
      "level": 58,
      "maxLevel": 99,
      "faction": "史莱克学院任职教师",
      "branch": 1,
      "martialSoulTypes": [
        "器武魂"
      ],
      "martialSouls": [
        "混天披风"
      ],
      "talents": [],
      "traits": [
        "启蒙期·6-11岁",
        "成长期·12-17岁",
        "担当期·18岁+",
        "精英职责·18岁+·50级+"
      ],
      "domains": [],
      "rings": [
        {
          "index": 1,
          "years": 300,
          "description": "300年魂环"
        },
        {
          "index": 2,
          "years": 700,
          "description": "700年魂环"
        },
        {
          "index": 3,
          "years": 1800,
          "description": "1800年魂环"
        },
        {
          "index": 4,
          "years": 1000,
          "description": "1000年魂环"
        },
        {
          "index": 5,
          "years": 10000,
          "description": "10000年魂环"
        }
      ],
      "soulBones": [
        "300年外附魂骨",
        "300年右腿骨",
        "700年左腿骨",
        "1800年左臂骨",
        "1000年躯干骨",
        "10000年右臂骨"
      ],
      "beast": null,
      "godTrial": {
        "tier": "三级",
        "deity": "",
        "completed": 0,
        "total": 7
      },
      "queue": [],
      "activeTask": null,
      "lastPool": "三级神考抽取池（三级神一共7考）",
      "lastOptionId": "5e5c3a",
      "lastResult": "自创神位（自定义神名，三级神，7考）",
      "lastProbability": 0.16666666666666666,
      "logs": [
        {
          "id": "0-0-1784216934639",
          "step": 0,
          "title": "命运启封",
          "text": "种子：mrnop1p1-0pln8351a8tizu-sample-002",
          "tone": "major",
          "time": "时间未定"
        },
        {
          "id": "1-1-1784216934639",
          "step": 1,
          "title": "基础设定3:你的性别是？",
          "text": "男",
          "tone": "normal",
          "time": "时间未定"
        },
        {
          "id": "2-2-1784216934640",
          "step": 2,
          "title": "基础设定4:容貌（B级以下无法恋爱）",
          "text": "E级（有点丑）",
          "tone": "normal",
          "time": "时间未定"
        },
        {
          "id": "3-3-1784216934640",
          "step": 3,
          "title": "基础设定5:武魂天赋",
          "text": "器武魂",
          "tone": "normal",
          "time": "时间未定"
        },
        {
          "id": "4-4-1784216934640",
          "step": 4,
          "title": "器武魂分类",
          "text": "披风锁链",
          "tone": "normal",
          "time": "时间未定"
        },
        {
          "id": "5-5-1784216934640",
          "step": 5,
          "title": "器武魂：披风锁链",
          "text": "混天披风",
          "tone": "normal",
          "time": "时间未定"
        },
        {
          "id": "6-6-1784216934640",
          "step": 6,
          "title": "基础设定6:是否拥有特殊天赋",
          "text": "否",
          "tone": "normal",
          "time": "时间未定"
        },
        {
          "id": "7-7-1784216934640",
          "step": 7,
          "title": "基础设定7:你的年龄",
          "text": "6岁",
          "tone": "normal",
          "time": "6岁"
        },
        {
          "id": "8-8-1784216934640",
          "step": 8,
          "title": "基础设定8:穿越时期",
          "text": "唐三8岁",
          "tone": "normal",
          "time": "唐三 8 岁"
        },
        {
          "id": "9-9-1784216934640",
          "step": 9,
          "title": "先天魂力（6岁限定）",
          "text": "4级",
          "tone": "normal",
          "time": "唐三 8 岁"
        },
        {
          "id": "10-10-1784216934641",
          "step": 10,
          "title": "人物背景or加入的势力（6岁限定）",
          "text": "诺丁初级魂师学院",
          "tone": "normal",
          "time": "唐三 8 岁"
        },
        {
          "id": "11-11-1784216934641",
          "step": 11,
          "title": "势力专属剧情：天斗学院体系",
          "text": "【启蒙期·6-11岁】学院安排你参加基础联考，你靠稳定魂力控制通过第一次分班",
          "tone": "normal",
          "time": "唐三 8 岁"
        },
        {
          "id": "12-12-1784216934641",
          "step": 12,
          "title": "2年后，你的成长（6岁-12岁限定，已达12岁则不可再抽取该池）",
          "text": "等级+6",
          "tone": "good",
          "time": "唐三 10 岁"
        },
        {
          "id": "13-13-1784216934641",
          "step": 13,
          "title": "是否获得特殊成长经历（每次经过一次时间跳跃，可抽取该池）",
          "text": "否，无事发生",
          "tone": "normal",
          "time": "唐三 10 岁"
        },
        {
          "id": "14-14-1784216934641",
          "step": 14,
          "title": "魂环吸收（第一魂环）（抽取完魂环后请进入对应的魂骨抽奖池）",
          "text": "300年魂环",
          "tone": "normal",
          "time": "唐三 10 岁"
        },
        {
          "id": "15-15-1784216934642",
          "step": 15,
          "title": "魂骨抽取池（已拥有部位则重抽）",
          "text": "外附魂骨",
          "tone": "normal",
          "time": "唐三 10 岁"
        },
        {
          "id": "16-16-1784216934642",
          "step": 16,
          "title": "2年后，你的成长（6岁-12岁限定，已达12岁则不可再抽取该池）",
          "text": "等级+4",
          "tone": "good",
          "time": "唐三 12 岁"
        },
        {
          "id": "17-17-1784216934642",
          "step": 17,
          "title": "是否获得特殊成长经历（每次经过一次时间跳跃，可抽取该池）",
          "text": "是",
          "tone": "normal",
          "time": "唐三 12 岁"
        },
        {
          "id": "18-18-1784216934642",
          "step": 18,
          "title": "特殊成长经历",
          "text": "获得神考（要求15岁以下40级以上，20岁以下60级以上，25岁以下70级以上，30岁以下90级以上，否则重抽）（已拥有神考无法叠加则重抽）",
          "tone": "good",
          "time": "唐三 12 岁"
        },
        {
          "id": "19-19-1784216934642",
          "step": 19,
          "title": "神考池子",
          "text": "二级神考核",
          "tone": "normal",
          "time": "唐三 12 岁"
        },
        {
          "id": "20-20-1784216934643",
          "step": 20,
          "title": "二级神考抽取池（二级神一共8考）",
          "text": "自创神位（自定义神名，二级神，8考）",
          "tone": "major",
          "time": "唐三 12 岁"
        },
        {
          "id": "21-21-1784216934643",
          "step": 21,
          "title": "剧情1:是否参与入学剧情（非史莱克or武魂殿学员限定）",
          "text": "是",
          "tone": "normal",
          "time": "唐三 12 岁"
        },
        {
          "id": "22-22-1784216934643",
          "step": 22,
          "title": "剧情2:在校2年的经历选择（非史莱克or武魂殿学员限定）",
          "text": "默默无闻，一直闭关",
          "tone": "normal",
          "time": "唐三 12 岁"
        },
        {
          "id": "23-23-1784216934643",
          "step": 23,
          "title": "2年后，你的成长（6岁-12岁限定，已达12岁则不可再抽取该池）",
          "text": "等级+4",
          "tone": "good",
          "time": "唐三 14 岁"
        },
        {
          "id": "24-24-1784216934643",
          "step": 24,
          "title": "是否获得特殊成长经历（每次经过一次时间跳跃，可抽取该池）",
          "text": "否，无事发生",
          "tone": "normal",
          "time": "唐三 14 岁"
        },
        {
          "id": "25-25-1784216934644",
          "step": 25,
          "title": "加入的势力（12岁限定）",
          "text": "五元素学院",
          "tone": "normal",
          "time": "唐三 14 岁"
        },
        {
          "id": "26-26-1784216934644",
          "step": 26,
          "title": "势力专属剧情：天斗学院体系",
          "text": "【成长期·12-17岁】你参加学院交流赛，以一次主动换位挽回被压制的小队",
          "tone": "normal",
          "time": "唐三 14 岁"
        },
        {
          "id": "27-27-1784216934644",
          "step": 27,
          "title": "剧情3:是否参与参加团队核心竞争（魂师大赛前限定抽取池，此时唐三14岁）",
          "text": "否，你不感兴趣（默认不参加魂师学院大赛剧情）",
          "tone": "normal",
          "time": "唐三 14 岁"
        },
        {
          "id": "28-28-1784216934645",
          "step": 28,
          "title": "剧情4:魂师学院大赛预选赛结果",
          "text": "拖后腿，导致团队落败（35级以下限定，高于35级则重抽）",
          "tone": "normal",
          "time": "唐三 14 岁"
        },
        {
          "id": "29-29-1784216934645",
          "step": 29,
          "title": "剧情5:单人赛结果",
          "text": "因为你的自傲，开局被唐三击败，你的学院单人赛落败（45+级则可以重抽）",
          "tone": "normal",
          "time": "唐三 14 岁"
        },
        {
          "id": "30-30-1784216934645",
          "step": 30,
          "title": "剧情6:决赛结果",
          "text": "与队友配合对战黄金一代重伤获胜（45+限定，否则重抽）",
          "tone": "bad",
          "time": "唐三 14 岁"
        },
        {
          "id": "31-31-1784216934645",
          "step": 31,
          "title": "2年后，你的成长（12岁-18岁限定，已达18岁不可再抽取该池）（没有神位最多到99级）",
          "text": "等级+4级",
          "tone": "good",
          "time": "唐三 16 岁"
        },
        {
          "id": "32-32-1784216934645",
          "step": 32,
          "title": "是否获得特殊成长经历（每次经过一次时间跳跃，可抽取该池）",
          "text": "是",
          "tone": "normal",
          "time": "唐三 16 岁"
        },
        {
          "id": "33-33-1784216934646",
          "step": 33,
          "title": "特殊成长经历",
          "text": "获得对应吸收上限的魂骨（进入魂骨抽取池）",
          "tone": "good",
          "time": "唐三 16 岁"
        },
        {
          "id": "34-34-1784216934646",
          "step": 34,
          "title": "魂骨抽取池（已拥有部位则重抽）",
          "text": "右腿骨",
          "tone": "normal",
          "time": "唐三 16 岁"
        },
        {
          "id": "35-35-1784216934646",
          "step": 35,
          "title": "魂环吸收（第二魂环）（抽取完魂环后请进入对应的魂骨抽奖池）",
          "text": "700年魂环",
          "tone": "normal",
          "time": "唐三 16 岁"
        },
        {
          "id": "36-36-1784216934646",
          "step": 36,
          "title": "魂骨抽取池（已拥有部位则重抽）",
          "text": "左腿骨",
          "tone": "normal",
          "time": "唐三 16 岁"
        },
        {
          "id": "37-37-1784216934646",
          "step": 37,
          "title": "2年后，你的成长（12岁-18岁限定，已达18岁不可再抽取该池）（没有神位最多到99级）",
          "text": "等级+8级",
          "tone": "good",
          "time": "唐三 18 岁"
        },
        {
          "id": "38-38-1784216934646",
          "step": 38,
          "title": "是否获得特殊成长经历（每次经过一次时间跳跃，可抽取该池）",
          "text": "是",
          "tone": "normal",
          "time": "唐三 18 岁"
        },
        {
          "id": "39-39-1784216934647",
          "step": 39,
          "title": "特殊成长经历",
          "text": "略有领悟（等级+3）",
          "tone": "good",
          "time": "唐三 18 岁"
        },
        {
          "id": "40-40-1784216934647",
          "step": 40,
          "title": "魂环吸收（第三魂环）（抽取完魂环后请进入对应的魂骨抽奖池）",
          "text": "1800年魂环",
          "tone": "normal",
          "time": "唐三 18 岁"
        },
        {
          "id": "41-41-1784216934647",
          "step": 41,
          "title": "魂骨抽取池（已拥有部位则重抽）",
          "text": "左臂骨",
          "tone": "normal",
          "time": "唐三 18 岁"
        },
        {
          "id": "42-42-1784216934647",
          "step": 42,
          "title": "是否进入杀戮之都（角色在16岁~22岁限定事件，未满足年龄不能抽取）",
          "text": "否",
          "tone": "normal",
          "time": "唐三 18 岁"
        },
        {
          "id": "43-43-1784216934647",
          "step": 43,
          "title": "2年后，你的成长（12岁-18岁限定，已达18岁不可再抽取该池）（没有神位最多到99级）",
          "text": "等级+9级",
          "tone": "good",
          "time": "唐三 20 岁"
        },
        {
          "id": "44-44-1784216934647",
          "step": 44,
          "title": "是否获得特殊成长经历（每次经过一次时间跳跃，可抽取该池）",
          "text": "否，无事发生",
          "tone": "normal",
          "time": "唐三 20 岁"
        },
        {
          "id": "45-45-1784216934648",
          "step": 45,
          "title": "魂环吸收（第四魂环）（抽取完魂环后请进入对应的魂骨抽奖池）",
          "text": "1000年魂环",
          "tone": "normal",
          "time": "唐三 20 岁"
        },
        {
          "id": "46-46-1784216934648",
          "step": 46,
          "title": "魂骨抽取池（已拥有部位则重抽）",
          "text": "躯干骨",
          "tone": "normal",
          "time": "唐三 20 岁"
        },
        {
          "id": "47-47-1784216934648",
          "step": 47,
          "title": "二级神考核第一考奖励（要求40级以上才可以抽取）",
          "text": "获得一块6万年魂骨（进入魂骨抽取池）",
          "tone": "good",
          "time": "唐三 20 岁"
        },
        {
          "id": "48-48-1784216934648",
          "step": 48,
          "title": "加入的势力（18岁限定）",
          "text": "史莱克学院任职教师（进入剧情分支一）",
          "tone": "normal",
          "time": "唐三 20 岁"
        },
        {
          "id": "49-49-1784216934648",
          "step": 49,
          "title": "势力专属剧情：史莱克学院",
          "text": "【担当期·18岁+】你协助学院整理学员魂环风险档案，开始承担正式教学或护校事务",
          "tone": "normal",
          "time": "唐三 20 岁"
        },
        {
          "id": "50-50-1784216934649",
          "step": 50,
          "title": "剧情14:是否参与天斗宫变（此时唐三20岁）",
          "text": "是，在外围援护",
          "tone": "normal",
          "time": "唐三 20 岁"
        },
        {
          "id": "51-51-1784216934649",
          "step": 51,
          "title": "剧情15:唐三重建唐门，邀请你加入唐门担任其中一个堂主or副门主的职位（70+级会邀请你当副门主，70级以下则堂主）",
          "text": "同意加入，但你婉拒堂主or副门主的职位",
          "tone": "good",
          "time": "唐三 20 岁"
        },
        {
          "id": "52-52-1784216934649",
          "step": 52,
          "title": "2年后，你的成长（18岁+的年龄通用池）（无神位最多只能达到99级）",
          "text": "等级+1",
          "tone": "good",
          "time": "唐三 22 岁"
        },
        {
          "id": "53-53-1784216934649",
          "step": 53,
          "title": "是否获得特殊成长经历（每次经过一次时间跳跃，可抽取该池）",
          "text": "否，无事发生",
          "tone": "normal",
          "time": "唐三 22 岁"
        },
        {
          "id": "54-54-1784216934649",
          "step": 54,
          "title": "剧情16:七怪打算前往海神岛，你是否前往（唐三21岁限定）",
          "text": "是，前往海神岛（进入海神考核奖池选择你的考核）",
          "tone": "normal",
          "time": "唐三 22 岁"
        },
        {
          "id": "55-55-1784216934650",
          "step": 55,
          "title": "2年后，你的成长（18岁+的年龄通用池）（无神位最多只能达到99级）",
          "text": "等级+9",
          "tone": "good",
          "time": "唐三 24 岁"
        },
        {
          "id": "56-56-1784216934650",
          "step": 56,
          "title": "是否获得特殊成长经历（每次经过一次时间跳跃，可抽取该池）",
          "text": "是",
          "tone": "normal",
          "time": "唐三 24 岁"
        },
        {
          "id": "57-57-1784216934650",
          "step": 57,
          "title": "特殊成长经历",
          "text": "略有领悟（等级+3）",
          "tone": "good",
          "time": "唐三 24 岁"
        },
        {
          "id": "58-58-1784216934650",
          "step": 58,
          "title": "魂环吸收（第五魂环）（抽取完魂环后请进入对应的魂骨抽奖池）",
          "text": "10000年魂环",
          "tone": "normal",
          "time": "唐三 24 岁"
        },
        {
          "id": "59-59-1784216934650",
          "step": 59,
          "title": "魂骨抽取池（已拥有部位则重抽）",
          "text": "右臂骨",
          "tone": "normal",
          "time": "唐三 24 岁"
        },
        {
          "id": "60-60-1784216934651",
          "step": 60,
          "title": "二级神考核第二考奖励（要求50级以上才可抽取）",
          "text": "获得一块7万年魂骨（进入魂骨抽取池）",
          "tone": "good",
          "time": "唐三 24 岁"
        },
        {
          "id": "61-61-1784216934652",
          "step": 61,
          "title": "势力专属剧情：史莱克学院",
          "text": "【精英职责·18岁+·50级+】你受托审查高年级实战考核，在关键时刻叫停一场失控对决",
          "tone": "normal",
          "time": "唐三 24 岁"
        },
        {
          "id": "62-62-1784216934652",
          "step": 62,
          "title": "2年后，你的成长（18岁+的年龄通用池）（无神位最多只能达到99级）",
          "text": "等级+3",
          "tone": "good",
          "time": "唐三 26 岁"
        },
        {
          "id": "63-63-1784216934652",
          "step": 63,
          "title": "是否获得特殊成长经历（每次经过一次时间跳跃，可抽取该池）",
          "text": "是",
          "tone": "normal",
          "time": "唐三 26 岁"
        },
        {
          "id": "64-64-1784216934653",
          "step": 64,
          "title": "特殊成长经历",
          "text": "获得神考（要求15岁以下40级以上，20岁以下60级以上，25岁以下70级以上，30岁以下90级以上，否则重抽）（已拥有神考无法叠加则重抽）",
          "tone": "good",
          "time": "唐三 26 岁"
        },
        {
          "id": "65-65-1784216934653",
          "step": 65,
          "title": "神考池子",
          "text": "三级神考核",
          "tone": "normal",
          "time": "唐三 26 岁"
        },
        {
          "id": "66-66-1784216934654",
          "step": 66,
          "title": "三级神考抽取池（三级神一共7考）",
          "text": "自创神位（自定义神名，三级神，7考）",
          "tone": "major",
          "time": "唐三 26 岁"
        },
        {
          "id": "66-67-1784216934654",
          "step": 66,
          "title": "命运终章",
          "text": "你走过斗罗大陆主线年代，命运进入新的时代。",
          "tone": "major",
          "time": "唐三 26 岁"
        }
      ],
      "flags": {
        "toolMartialSoulCategory": "披风锁链",
        "factionHistory": "诺丁初级魂师学院｜五元素学院｜史莱克学院任职教师",
        "factionId": "shrek",
        "faction:6": true,
        "factionStory:academy:junior": true,
        "result:势力专属剧情：天斗学院体系": "【成长期·12-17岁】你参加学院交流赛，以一次主动换位挽回被压制的小队",
        "_noGodCount": 0,
        "story:3@12": true,
        "result:剧情1:是否参与入学剧情（非史莱克or武魂殿学员限定）": "是",
        "result:剧情2:在校2年的经历选择（非史莱克or武魂殿学员限定）": "默默无闻，一直闭关",
        "faction:12": true,
        "factionStory:academy:youth": true,
        "story:3@14": true,
        "result:剧情3:是否参与参加团队核心竞争（魂师大赛前限定抽取池，此时唐三14岁）": "否，你不感兴趣（默认不参加魂师学院大赛剧情）",
        "result:剧情4:魂师学院大赛预选赛结果": "拖后腿，导致团队落败（35级以下限定，高于35级则重抽）",
        "result:剧情5:单人赛结果": "因为你的自傲，开局被唐三击败，你的学院单人赛落败（45+级则可以重抽）",
        "result:剧情6:决赛结果": "与队友配合对战黄金一代重伤获胜（45+限定，否则重抽）",
        "slaughter": true,
        "result:是否进入杀戮之都（角色在16岁~22岁限定事件，未满足年龄不能抽取）": "否",
        "story:1@12": true,
        "story:1@14": true,
        "story:1@19": true,
        "faction:18": true,
        "factionStory:shrek:adult": true,
        "result:势力专属剧情：史莱克学院": "【精英职责·18岁+·50级+】你受托审查高年级实战考核，在关键时刻叫停一场失控对决",
        "story:1@20": true,
        "result:剧情14:是否参与天斗宫变（此时唐三20岁）": "是，在外围援护",
        "result:剧情15:唐三重建唐门，邀请你加入唐门担任其中一个堂主or副门主的职位（70+级会邀请你当副门主，70级以下则堂主）": "同意加入，但你婉拒堂主or副门主的职位",
        "story:1@21": true,
        "result:剧情16:七怪打算前往海神岛，你是否前往（唐三21岁限定）": "是，前往海神岛（进入海神考核奖池选择你的考核）",
        "factionStory:shrek:elite": true,
        "_pendingCustomGod": "三级"
      },
      "alive": true,
      "ending": "你走过斗罗大陆主线年代，命运进入新的时代。",
      "resumeState": null,
      "settings": {
        "softenText": false,
        "spinDuration": 900
      }
    }
  }
}
